openpi_client/__init__.py
openpi_client/action_chunk_broker.py
openpi_client/base_policy.py
openpi_client/image_tools.py
openpi_client/image_tools_test.py
openpi_client/msgpack_numpy.py
openpi_client/msgpack_numpy_test.py
openpi_client/websocket_client_policy.py
openpi_client/runtime/agent.py
openpi_client/runtime/environment.py
openpi_client/runtime/runtime.py
openpi_client/runtime/subscriber.py
openpi_client/runtime/agents/policy_agent.py
openpi_client-0.1.1.dist-info/METADATA
openpi_client-0.1.1.dist-info/WHEEL
openpi_client-0.1.1.dist-info/licenses/LICENSE
openpi_client-0.1.1.dist-info/RECORD
