Metadata-Version: 2.4
Name: openpi-client
Version: 0.1.1
Summary: Runs openpi policy interface by websocket connection to a server.
License-File: LICENSE
Requires-Python: >=3.7
Requires-Dist: dm-tree>=0.1.8
Requires-Dist: msgpack>=1.0.5
Requires-Dist: numpy<2.0.0,>=1.22.4
Requires-Dist: pillow>=9.0.0
Requires-Dist: websockets>=11.0
